ghostdata/__init__.py
ghostdata/cleaner.py
ghostdata-1.0.1.dist-info/METADATA
ghostdata-1.0.1.dist-info/WHEEL
ghostdata-1.0.1.dist-info/top_level.txt
ghostdata-1.0.1.dist-info/RECORD
