Metadata-Version: 2.2
Name: ghostdata
Version: 1.0.1
Summary: GhostData: Securely remove metadata from images, PDFs, videos, and audio files.
Home-page: https://github.com/oxde/ghostdata
Author: Oxde
Author-email: your-email@example.com
License: CC BY-NC 4.0
Classifier: Programming Language :: Python :: 3
Classifier: License :: Other/Proprietary License
Classifier: Operating System :: OS Independent
Requires-Python: >=3.6
Requires-Dist: pillow
Requires-Dist: pypdf
Requires-Dist: mutagen
Requires-Dist: imageio[ffmpeg]
Requires-Dist: ffmpeg-python
Dynamic: author
Dynamic: author-email
Dynamic: classifier
Dynamic: description
Dynamic: description-content-type
Dynamic: home-page
Dynamic: license
Dynamic: requires-dist
Dynamic: requires-python
Dynamic: summary
